xfq5/__init__.py
xfq55-0.0.1.dist-info/METADATA
xfq55-0.0.1.dist-info/WHEEL
xfq55-0.0.1.dist-info/top_level.txt
xfq55-0.0.1.dist-info/RECORD
